--- openjdk-17.0.1/SuppressionXpathRegressionNestedTryDepth.class
+++ openjdk-17.0.4/SuppressionXpathRegressionNestedTryDepth.class
├── javap -verbose -constants -s -l -private {}
│ @@ -1,36 +1,33 @@
│ -  SHA-256 checksum d9831181d61f4889039c9b4dc8843e881c16fff9459ce7aabe2b6f90b3ca52e9
│ +  SHA-256 checksum 82f4139dd5ddaa067af01a6d102fd16ed89100c62eb6b01226579508fb8731f9
│    Compiled from "SuppressionXpathRegressionNestedTryDepth.java"
│  public class org.checkstyle.suppressionxpathfilter.nestedtrydepth.SuppressionXpathRegressionNestedTryDepth
│    minor version: 0
│    major version: 55
│    flags: (0x0021) ACC_PUBLIC, ACC_SUPER
│ -  this_class: #9                          // org/checkstyle/suppressionxpathfilter/nestedtrydepth/SuppressionXpathRegressionNestedTryDepth
│ +  this_class: #7                          // org/checkstyle/suppressionxpathfilter/nestedtrydepth/SuppressionXpathRegressionNestedTryDepth
│    super_class: #2                         // java/lang/Object
│    interfaces: 0, fields: 0, methods: 2, attributes: 1
│  Constant pool:
│     #1 = Methodref          #2.#3          // java/lang/Object."<init>":()V
│     #2 = Class              #4             // java/lang/Object
│     #3 = NameAndType        #5:#6          // "<init>":()V
│     #4 = Utf8               java/lang/Object
│     #5 = Utf8               <init>
│     #6 = Utf8               ()V
│ -   #7 = Class              #8             // java/lang/Exception
│ -   #8 = Utf8               java/lang/Exception
│ -   #9 = Class              #10            // org/checkstyle/suppressionxpathfilter/nestedtrydepth/SuppressionXpathRegressionNestedTryDepth
│ -  #10 = Utf8               org/checkstyle/suppressionxpathfilter/nestedtrydepth/SuppressionXpathRegressionNestedTryDepth
│ -  #11 = Utf8               Code
│ -  #12 = Utf8               LineNumberTable
│ -  #13 = Utf8               LocalVariableTable
│ -  #14 = Utf8               this
│ -  #15 = Utf8               Lorg/checkstyle/suppressionxpathfilter/nestedtrydepth/SuppressionXpathRegressionNestedTryDepth;
│ -  #16 = Utf8               test
│ -  #17 = Utf8               StackMapTable
│ -  #18 = Utf8               SourceFile
│ -  #19 = Utf8               SuppressionXpathRegressionNestedTryDepth.java
│ +   #7 = Class              #8             // org/checkstyle/suppressionxpathfilter/nestedtrydepth/SuppressionXpathRegressionNestedTryDepth
│ +   #8 = Utf8               org/checkstyle/suppressionxpathfilter/nestedtrydepth/SuppressionXpathRegressionNestedTryDepth
│ +   #9 = Utf8               Code
│ +  #10 = Utf8               LineNumberTable
│ +  #11 = Utf8               LocalVariableTable
│ +  #12 = Utf8               this
│ +  #13 = Utf8               Lorg/checkstyle/suppressionxpathfilter/nestedtrydepth/SuppressionXpathRegressionNestedTryDepth;
│ +  #14 = Utf8               test
│ +  #15 = Utf8               SourceFile
│ +  #16 = Utf8               SuppressionXpathRegressionNestedTryDepth.java
│  {
│    public org.checkstyle.suppressionxpathfilter.nestedtrydepth.SuppressionXpathRegressionNestedTryDepth();
│      descriptor: ()V
│      flags: (0x0001) ACC_PUBLIC
│      Code:
│        stack=1, locals=1, args_size=1
│           0: aload_0
│ @@ -42,29 +39,16 @@
│          Start  Length  Slot  Name   Signature
│              0       5     0  this   Lorg/checkstyle/suppressionxpathfilter/nestedtrydepth/SuppressionXpathRegressionNestedTryDepth;
│  
│    public void test();
│      descriptor: ()V
│      flags: (0x0001) ACC_PUBLIC
│      Code:
│ -      stack=1, locals=2, args_size=1
│ -         0: goto          3
│ -         3: goto          7
│ -         6: astore_1
│ -         7: return
│ -      Exception table:
│ -         from    to  target type
│ -             0     3     6   Class java/lang/Exception
│ +      stack=0, locals=1, args_size=1
│ +         0: return
│        LineNumberTable:
│ -        line 10: 0
│ -        line 11: 3
│ -        line 12: 7
│ +        line 12: 0
│        LocalVariableTable:
│          Start  Length  Slot  Name   Signature
│ -            0       8     0  this   Lorg/checkstyle/suppressionxpathfilter/nestedtrydepth/SuppressionXpathRegressionNestedTryDepth;
│ -      StackMapTable: number_of_entries = 3
│ -        frame_type = 3 /* same */
│ -        frame_type = 66 /* same_locals_1_stack_item */
│ -          stack = [ class java/lang/Exception ]
│ -        frame_type = 0 /* same */
│ +            0       1     0  this   Lorg/checkstyle/suppressionxpathfilter/nestedtrydepth/SuppressionXpathRegressionNestedTryDepth;
│  }
│  SourceFile: "SuppressionXpathRegressionNestedTryDepth.java"
