--- openjdk-15.0.1/PropertyListParser$JJCalls.class
+++ ecj-3.24.0_openjdk-11.0.19/PropertyListParser$JJCalls.class
├── javap -verbose -constants -s -l -private {}
│ @@ -1,33 +1,33 @@
│ -  SHA-256 checksum 953fe0530aa900413b3447d9d920ee6bc0271074dd7ba52302ec1c785f004f35
│ +  SHA-256 checksum 6c89e3232c0c2c0988c3e2971f24db6c35f5fb80deb488adc23f45127a7e3bc3
│    Compiled from "PropertyListParser.java"
│  final class org.apache.commons.configuration2.plist.PropertyListParser$JJCalls
│    minor version: 0
│    major version: 52
│    flags: (0x0030) ACC_FINAL, ACC_SUPER
│ -  this_class: #7                          // org/apache/commons/configuration2/plist/PropertyListParser$JJCalls
│ -  super_class: #2                         // java/lang/Object
│ +  this_class: #1                          // org/apache/commons/configuration2/plist/PropertyListParser$JJCalls
│ +  super_class: #3                         // java/lang/Object
│    interfaces: 0, fields: 4, methods: 1, attributes: 2
│  Constant pool:
│ -   #1 = Methodref          #2.#3          // java/lang/Object."<init>":()V
│ -   #2 = Class              #4             // java/lang/Object
│ -   #3 = NameAndType        #5:#6          // "<init>":()V
│ +   #1 = Class              #2             // org/apache/commons/configuration2/plist/PropertyListParser$JJCalls
│ +   #2 = Utf8               org/apache/commons/configuration2/plist/PropertyListParser$JJCalls
│ +   #3 = Class              #4             // java/lang/Object
│     #4 = Utf8               java/lang/Object
│ -   #5 = Utf8               <init>
│ -   #6 = Utf8               ()V
│ -   #7 = Class              #8             // org/apache/commons/configuration2/plist/PropertyListParser$JJCalls
│ -   #8 = Utf8               org/apache/commons/configuration2/plist/PropertyListParser$JJCalls
│ -   #9 = Utf8               gen
│ -  #10 = Utf8               I
│ -  #11 = Utf8               first
│ -  #12 = Utf8               Lorg/apache/commons/configuration2/plist/Token;
│ -  #13 = Utf8               arg
│ -  #14 = Utf8               next
│ -  #15 = Utf8               Lorg/apache/commons/configuration2/plist/PropertyListParser$JJCalls;
│ -  #16 = Utf8               Code
│ +   #5 = Utf8               gen
│ +   #6 = Utf8               I
│ +   #7 = Utf8               first
│ +   #8 = Utf8               Lorg/apache/commons/configuration2/plist/Token;
│ +   #9 = Utf8               arg
│ +  #10 = Utf8               next
│ +  #11 = Utf8               Lorg/apache/commons/configuration2/plist/PropertyListParser$JJCalls;
│ +  #12 = Utf8               <init>
│ +  #13 = Utf8               ()V
│ +  #14 = Utf8               Code
│ +  #15 = Methodref          #3.#16         // java/lang/Object."<init>":()V
│ +  #16 = NameAndType        #12:#13        // "<init>":()V
│    #17 = Utf8               LineNumberTable
│    #18 = Utf8               LocalVariableTable
│    #19 = Utf8               this
│    #20 = Utf8               SourceFile
│    #21 = Utf8               PropertyListParser.java
│    #22 = Utf8               InnerClasses
│    #23 = Class              #24            // org/apache/commons/configuration2/plist/PropertyListParser
│ @@ -52,18 +52,18 @@
│  
│    org.apache.commons.configuration2.plist.PropertyListParser$JJCalls();
│      descriptor: ()V
│      flags: (0x0000)
│      Code:
│        stack=1, locals=1, args_size=1
│           0: aload_0
│ -         1: invokespecial #1                  // Method java/lang/Object."<init>":()V
│ +         1: invokespecial #15                 // Method java/lang/Object."<init>":()V
│           4: return
│        LineNumberTable:
│          line 629: 0
│        LocalVariableTable:
│          Start  Length  Slot  Name   Signature
│              0       5     0  this   Lorg/apache/commons/configuration2/plist/PropertyListParser$JJCalls;
│  }
│  SourceFile: "PropertyListParser.java"
│  InnerClasses:
│ -  static final #25= #7 of #23;            // JJCalls=class org/apache/commons/configuration2/plist/PropertyListParser$JJCalls of class org/apache/commons/configuration2/plist/PropertyListParser
│ +  static final #25= #1 of #23;            // JJCalls=class org/apache/commons/configuration2/plist/PropertyListParser$JJCalls of class org/apache/commons/configuration2/plist/PropertyListParser
